csvw_functions_extra/__init__.py
csvw_functions_extra/csvw_functions_extra.py
csvw_functions_extra-0.0.0.dist-info/LICENSE
csvw_functions_extra-0.0.0.dist-info/METADATA
csvw_functions_extra-0.0.0.dist-info/WHEEL
csvw_functions_extra-0.0.0.dist-info/top_level.txt
csvw_functions_extra-0.0.0.dist-info/RECORD
