Metadata-Version: 2.1
Name: csvw_functions_extra
Version: 0.0.0
Summary: Python functions for CSVW files providing extra functionality beyond the CSVW standards
Home-page: https://github.com/stevenkfirth/csvw_functions_extra
Author: Steven Firth
Author-email: Steven Firth <s.k.firth@lboro.ac.uk>
Project-URL: Homepage, https://github.com/stevenkfirth/csvw_functions_extra
Project-URL: Issues, https://github.com/stevenkfirth/csvw_functions_extra/issues
Classifier: Programming Language :: Python :: 3
Classifier: License :: OSI Approved :: MIT License
Classifier: Operating System :: OS Independent
Requires-Python: >=3.6
License-File: LICENSE
Requires-Dist: csvw-functions >=0.0.0
